Workbook

Sheet Sales_Data
A1: Order_ID | B1: Order_Date | C1: Year | D1: Month | E1: Customer | F1: Segment | G1: Region | H1: Salesperson | I1: Category | J1: Product | K1: Quantity | L1: Unit_Price | M1: Total_Amount | N1: Payment_Method | O1: Status
A2: 1 | B2: 45985 | C2: 2025 | D2: Nov | E2: Customer 009 | F2: Corporate | G2: Midwest | H2: Bruno Lima | I2: Smartphones | J2: Phone Alpha | K2: 3 | L2: 1453.11 | M2: 4359.33 | N2: Bank Transfer | O2: Delivered
A3: 2 | B3: 45705 | C3: 2025 | D3: Feb | E3: Customer 036 | F3: Retail | G3: Midwest | H3: Gabriel Santos | I3: Laptops | J3: Laptop Pro | K3: 5 | L3: 5363.87 | M3: 26819.35 | N3: PIX | O3: Delivered
A4: 3 | B4: 45800 | C4: 2025 | D4: May | E4: Customer 010 | F4: Retail | G4: Northeast | H4: Bruno Lima | I4: Smartphones | J4: Phone Nova | K4: 4 | L4: 2156.85 | M4: 8627.4 | N4: Credit Card | O4: Delivered
A5: 4 | B5: 45841 | C5: 2025 | D5: Jul | E5: Customer 035 | F5: Retail | G5: North | H5: Bruno Lima | I5: Accessories | J5: USB-C Hub | K5: 1 | L5: 225.04 | M5: 225.04 | N5: Boleto | O5: Cancelled
A6: 5 | B6: 45974 | C6: 2025 | D6: Nov | E6: Customer 015 | F6: Corporate | G6: Southeast | H6: Daniel Rocha | I6: Accessories | J6: Mechanical Keyboard | K6: 1 | L6: 329.98 | M6: 329.98 | N6: Credit Card | O6: Delivered
A7: 6 | B7: 45890 | C7: 2025 | D7: Aug | E7: Customer 043 | F7: Retail | G7: Southeast | H7: Juliana Freitas | I7: Accessories | J7: Mechanical Keyboard | K7: 3 | L7: 342.94 | M7: 1028.82 | N7: PIX | O7: Delivered
A8: 7 | B8: 45783 | C8: 2025 | D8: May | E8: Customer 060 | F8: Corporate | G8: Midwest | H8: Daniel Rocha | I8: Laptops | J8: Laptop Gamer | K8: 4 | L8: 6805.78 | M8: 27223.12 | N8: Boleto | O8: Cancelled
A9: 8 | B9: 45686 | C9: 2025 | D9: Jan | E9: Customer 005 | F9: Retail | G9: Midwest | H9: Fernanda Melo | I9: Laptops | J9: Laptop Air | K9: 3 | L9: 3457.5 | M9: 10372.5 | N9: PIX | O9: Delivered
A10: 9 | B10: 45860 | C10: 2025 | D10: Jul | E10: Customer 048 | F10: Corporate | G10: Northeast | H10: Juliana Freitas | I10: Monitors | J10: Monitor 27 | K10: 3 | L10: 1242.83 | M10: 3728.49 | N10: Bank Transfer | O10: Cancelled
A11: 10 | B11: 45862 | C11: 2025 | D11: Jul | E11: Customer 006 | F11: Corporate | G11: Southeast | H11: Carlos Souza | I11: Accessories | J11: Mechanical Keyboard | K11: 2 | L11: 349.4 | M11: 698.8 | N11: PIX | O11: Delivered
A12: 11 | B12: 45874 | C12: 2025 | D12: Aug | E12: Customer 030 | F12: Retail | G12: Midwest | H12: Ana Costa | I12: Tablets | J12: Tablet Mini | K12: 4 | L12: 1181.97 | M12: 4727.88 | N12: Credit Card | O12: Delivered
A13: 12 | B13: 45932 | C13: 2025 | D13: Oct | E13: Customer 011 | F13: Retail | G13: Northeast | H13: Igor Ribeiro | I13: Accessories | J13: USB-C Hub | K13: 1 | L13: 213.57 | M13: 213.57 | N13: PIX | O13: Delivered
... A501: 500 | B501: 45805 | C501: 2025 | D501: May | E501: Customer 031 | F501: Retail | G501: South | H501: Igor Ribeiro | I501: Smartphones | J501: Phone Max | K501: 1 | L501: 2928.87 | M501: 2928.87 | N501: PIX | O501: Delivered

Sheet Dashboard
A1: DATA RETAIL ANALYTICS — EXECUTIVE DASHBOARD
A4: Region | C4: Segment | E4: Salesperson | G4: Category | I4: Status | K4: Payment
A5: All | C5: All | E5: All | G5: All | I5: All | K5: All
A7: Total Revenue | D7: Delivered Orders | G7: Average Ticket | J7: Cancellation Rate
A10: =SUMIFS(Sales_Data!$M$2:$M$501,Sales_Data!$G$2:$G$501,IF($A$5="All","*",$A$5),Sales_Data!$F$2:$F$501,IF($C$5="All","*",$C$5),Sales_Data!$H$2:$H$501,IF($E$5="All","*",$E$5),Sales_Data!$I$2:$I$501,IF($G$5="All","*",$G$5),Sales_Data!$O$2:$O$501,IF($I$5="All","*",$I$5),Sales_Data!$N$2:$N$501,IF($K$5="All","*",$K$5)) -> 3208552.9 | D10: =COUNTIFS(Sales_Data!$G$2:$G$501,IF($A$5="All","*",$A$5),Sales_Data!$F$2:$F$501,IF($C$5="All","*",$C$5),Sales_Data!$H$2:$H$501,IF($E$5="All","*",$E$5),Sales_Data!$I$2:$I$501,IF($G$5="All","*",$G$5),Sales_Data!$O$2:$O$501,"Delivered",Sales_Data!$N$2:$N$501,IF($K$5="All","*",$K$5)) -> 416 | G10: =IFERROR(SUMIFS(Sales_Data!$M$2:$M$501,Sales_Data!$G$2:$G$501,IF($A$5="All","*",$A$5),Sales_Data!$F$2:$F$501,IF($C$5="All","*",$C$5),Sales_Data!$H$2:$H$501,IF($E$5="All","*",$E$5),Sales_Data!$I$2:$I$501,IF($G$5="All","*",$G$5),Sales_Data!$O$2:$O$501,IF($I$5="All","*",$I$5),Sales_Data!$N$2:$N$501,IF($K$5="All","*",$K$5))/COUNTIFS(Sales_Data!$G$2:$G$501,IF($A$5="All","*",$A$5),Sales_Data!$F$2:$F$501,IF($C$5="All","*",$C$5),Sales_Data!$H$2:$H$501,IF($E$5="All","*",$E$5),Sales_Data!$I$2:$I$501,IF($G$5="All","*",$G$5),Sales_Data!$O$2:$O$501,IF($I$5="All","*",$I$5),Sales_Data!$N$2:$N$501,IF($K$5="All","*",$K$5)),0) -> 6417.1058 | J10: =IFERROR(COUNTIFS(Sales_Data!$G$2:$G$501,IF($A$5="All","*",$A$5),Sales_Data!$F$2:$F$501,IF($C$5="All","*",$C$5),Sales_Data!$H$2:$H$501,IF($E$5="All","*",$E$5),Sales_Data!$I$2:$I$501,IF($G$5="All","*",$G$5),Sales_Data!$O$2:$O$501,"Cancelled",Sales_Data!$N$2:$N$501,IF($K$5="All","*",$K$5))/COUNTIFS(Sales_Data!$G$2:$G$501,IF($A$5="All","*",$A$5),Sales_Data!$F$2:$F$501,IF($C$5="All","*",$C$5),Sales_Data!$H$2:$H$501,IF($E$5="All","*",$E$5),Sales_Data!$I$2:$I$501,IF($G$5="All","*",$G$5),Sales_Data!$N$2:$N$501,IF($K$5="All","*",$K$5)),0) -> 0.088
A16: Region | B16: Revenue | D16: Segment | E16: Revenue | G16: Month | H16: Revenue | J16: Salesperson | K16: Revenue
A17: Southeast | B17: =SUMIFS(Sales_Data!$M$2:$M$501,Sales_Data!$G$2:$G$501,A17,Sales_Data!$O$2:$O$501,"Delivered") -> 493850.55 | D17: Retail | E17: =SUMIFS(Sales_Data!$M$2:$M$501,Sales_Data!$F$2:$F$501,D17,Sales_Data!$O$2:$O$501,"Delivered") -> 1440149.4 | G17: Jan | H17: =SUMIFS(Sales_Data!$M$2:$M$501,Sales_Data!$D$2:$D$501,G17,Sales_Data!$O$2:$O$501,"Delivered") -> 168982.47 | J17: Ana Costa | K17: =SUMIFS(Sales_Data!$M$2:$M$501,Sales_Data!$H$2:$H$501,J17,Sales_Data!$O$2:$O$501,"Delivered") -> 255175
A18: South | B18: =SUMIFS(Sales_Data!$M$2:$M$501,Sales_Data!$G$2:$G$501,A18,Sales_Data!$O$2:$O$501,"Delivered") -> 529348.92 | D18: Corporate | E18: =SUMIFS(Sales_Data!$M$2:$M$501,Sales_Data!$F$2:$F$501,D18,Sales_Data!$O$2:$O$501,"Delivered") -> 909489.57 | G18: Feb | H18: =SUMIFS(Sales_Data!$M$2:$M$501,Sales_Data!$D$2:$D$501,G18,Sales_Data!$O$2:$O$501,"Delivered") -> 294995.93 | J18: Bruno Lima | K18: =SUMIFS(Sales_Data!$M$2:$M$501,Sales_Data!$H$2:$H$501,J18,Sales_Data!$O$2:$O$501,"Delivered") -> 323754.77
A19: Northeast | B19: =SUMIFS(Sales_Data!$M$2:$M$501,Sales_Data!$G$2:$G$501,A19,Sales_Data!$O$2:$O$501,"Delivered") -> 524141.42 | D19: Government | E19: =SUMIFS(Sales_Data!$M$2:$M$501,Sales_Data!$F$2:$F$501,D19,Sales_Data!$O$2:$O$501,"Delivered") -> 345973.73 | G19: Mar | H19: =SUMIFS(Sales_Data!$M$2:$M$501,Sales_Data!$D$2:$D$501,G19,Sales_Data!$O$2:$O$501,"Delivered") -> 221079.76 | J19: Carlos Souza | K19: =SUMIFS(Sales_Data!$M$2:$M$501,Sales_Data!$H$2:$H$501,J19,Sales_Data!$O$2:$O$501,"Delivered") -> 260833.44
A20: North | B20: =SUMIFS(Sales_Data!$M$2:$M$501,Sales_Data!$G$2:$G$501,A20,Sales_Data!$O$2:$O$501,"Delivered") -> 556106.49 | G20: Apr | H20: =SUMIFS(Sales_Data!$M$2:$M$501,Sales_Data!$D$2:$D$501,G20,Sales_Data!$O$2:$O$501,"Delivered") -> 156729.2 | J20: Daniel Rocha | K20: =SUMIFS(Sales_Data!$M$2:$M$501,Sales_Data!$H$2:$H$501,J20,Sales_Data!$O$2:$O$501,"Delivered") -> 225204.03
A21: Midwest | B21: =SUMIFS(Sales_Data!$M$2:$M$501,Sales_Data!$G$2:$G$501,A21,Sales_Data!$O$2:$O$501,"Delivered") -> 592165.35 | G21: May | H21: =SUMIFS(Sales_Data!$M$2:$M$501,Sales_Data!$D$2:$D$501,G21,Sales_Data!$O$2:$O$501,"Delivered") -> 344091.77 | J21: Eduarda Alves | K21: =SUMIFS(Sales_Data!$M$2:$M$501,Sales_Data!$H$2:$H$501,J21,Sales_Data!$O$2:$O$501,"Delivered") -> 250889.64
G22: Jun | H22: =SUMIFS(Sales_Data!$M$2:$M$501,Sales_Data!$D$2:$D$501,G22,Sales_Data!$O$2:$O$501,"Delivered") -> 261606.84 | J22: Fernanda Melo | K22: =SUMIFS(Sales_Data!$M$2:$M$501,Sales_Data!$H$2:$H$501,J22,Sales_Data!$O$2:$O$501,"Delivered") -> 338341.48
G23: Jul | H23: =SUMIFS(Sales_Data!$M$2:$M$501,Sales_Data!$D$2:$D$501,G23,Sales_Data!$O$2:$O$501,"Delivered") -> 246151.12 | J23: Gabriel Santos | K23: =SUMIFS(Sales_Data!$M$2:$M$501,Sales_Data!$H$2:$H$501,J23,Sales_Data!$O$2:$O$501,"Delivered") -> 367168.76
G24: Aug | H24: =SUMIFS(Sales_Data!$M$2:$M$501,Sales_Data!$D$2:$D$501,G24,Sales_Data!$O$2:$O$501,"Delivered") -> 165300.06 | J24: Helena Martins | K24: =SUMIFS(Sales_Data!$M$2:$M$501,Sales_Data!$H$2:$H$501,J24,Sales_Data!$O$2:$O$501,"Delivered") -> 270330.62
G25: Sep | H25: =SUMIFS(Sales_Data!$M$2:$M$501,Sales_Data!$D$2:$D$501,G25,Sales_Data!$O$2:$O$501,"Delivered") -> 241700.45 | J25: Igor Ribeiro | K25: =SUMIFS(Sales_Data!$M$2:$M$501,Sales_Data!$H$2:$H$501,J25,Sales_Data!$O$2:$O$501,"Delivered") -> 227764.91
G26: Oct | H26: =SUMIFS(Sales_Data!$M$2:$M$501,Sales_Data!$D$2:$D$501,G26,Sales_Data!$O$2:$O$501,"Delivered") -> 200395.66 | J26: Juliana Freitas | K26: =SUMIFS(Sales_Data!$M$2:$M$501,Sales_Data!$H$2:$H$501,J26,Sales_Data!$O$2:$O$501,"Delivered") -> 176150.08
G27: Nov | H27: =SUMIFS(Sales_Data!$M$2:$M$501,Sales_Data!$D$2:$D$501,G27,Sales_Data!$O$2:$O$501,"Delivered") -> 240424.46
G28: Dec | H28: =SUMIFS(Sales_Data!$M$2:$M$501,Sales_Data!$D$2:$D$501,G28,Sales_Data!$O$2:$O$501,"Delivered") -> 154155.01

Sheet Lists
A1: Region | B1: Segment | C1: Salesperson | D1: Category | E1: Status | F1: Payment
A2: All | B2: All | C2: All | D2: All | E2: All | F2: All
A3: Southeast | B3: Retail | C3: Ana Costa | D3: Smartphones | E3: Delivered | F3: Credit Card
A4: South | B4: Corporate | C4: Bruno Lima | D4: Laptops | E4: Cancelled | F4: PIX
A5: Northeast | B5: Government | C5: Carlos Souza | D5: Accessories | E5: Processing | F5: Boleto
A6: North | C6: Daniel Rocha | D6: Monitors | F6: Bank Transfer
A7: Midwest | C7: Eduarda Alves | D7: Tablets
C8: Fernanda Melo
C9: Gabriel Santos
C10: Helena Martins
C11: Igor Ribeiro
C12: Juliana Freitas

Sheet Instructions
A1: How to use this workbook
A4: 1 | B4: Open the Dashboard sheet.
A5: 2 | B5: Use the six dropdown filters at the top.
A6: 3 | B6: The KPI cards update automatically.
A7: 4 | B7: Use Sales_Data for detailed analysis and validation.
A8: 5 | B8: The workbook contains 500 fictional retail transactions for portfolio use.
A9: 6 | B9: Upload this file to the excel folder of your GitHub repository.
